llama_scheduler/__init__.py
llama_scheduler/__main__.py
llama_scheduler/cli.py
llama_scheduler/config.py
llama_scheduler/config_schema.py
llama_scheduler/core.py
llama_scheduler/job_functions.py
llama_scheduler/scheduler.py
llama_scheduler-0.1.0.dist-info/METADATA
llama_scheduler-0.1.0.dist-info/WHEEL
llama_scheduler-0.1.0.dist-info/licenses/LICENSE
llama_scheduler-0.1.0.dist-info/RECORD
